geoloaft/SampleMaker.py
geoloaft/ShapefileProcess.py
geoloaft/TifProcess.py
geoloaft/TifShpFilte.py
geoloaft/_init_.py
geolocr/SampleMaker.py
geolocr/ShapefileProcess.py
geolocr/TifProcess.py
geolocr/TifShpFilte.py
geolocr/_init_.py
geolode/SampleMaker.py
geolode/ShapefileProcess.py
geolode/TifProcess.py
geolode/TifShpFilte.py
geolode/_init_.py
GeoLoaft-1.0.1.1.dist-info/LICENSE.txt
GeoLoaft-1.0.1.1.dist-info/METADATA
GeoLoaft-1.0.1.1.dist-info/WHEEL
GeoLoaft-1.0.1.1.dist-info/top_level.txt
GeoLoaft-1.0.1.1.dist-info/RECORD
